fastproaudio/__init__.py
fastproaudio/_nbdev.py
fastproaudio/core.py
fastproaudio-0.0.2.dist-info/LICENSE
fastproaudio-0.0.2.dist-info/METADATA
fastproaudio-0.0.2.dist-info/WHEEL
fastproaudio-0.0.2.dist-info/entry_points.txt
fastproaudio-0.0.2.dist-info/top_level.txt
fastproaudio-0.0.2.dist-info/RECORD
