Metadata-Version: 2.1
Name: fastproaudio
Version: 0.0.2
Summary: End-to-end audio with fastai
Home-page: https://github.com/drscotthawley/fastproaudio/tree/master/
Author: Scott. Hawley
Author-email: scott.hawley@belmont.edu
License: Apache Software License 2.0
Keywords: audio neural networks
Platform: UNKNOWN
Classifier: Development Status :: 3 - Alpha
Classifier: Intended Audience :: Developers
Classifier: Natural Language :: English
Classifier: Programming Language :: Python :: 3.6
Classifier: Programming Language :: Python :: 3.7
Classifier: Programming Language :: Python :: 3.8
Classifier: License :: OSI Approved :: Apache Software License
Requires-Python: >=3.6
Requires-Dist: audioread
Requires-Dist: fastai
Requires-Dist: librosa
Requires-Dist: packaging
Requires-Dist: pip
Requires-Dist: pyzenodo3
Requires-Dist: soundfile
Requires-Dist: torchaudio
Provides-Extra: dev
